Workbook
Name Slicer_Category: #N/A
Name Slicer_Category_Type: #N/A
Name Slicer_Category1: #N/A
Name Slicer_month: #N/A

Sheet Sheet1
A1: Date | B1: Description | C1: Debit | D1: Credit | F1: Sub-category | G1: Category | H1: Category Type
A2: 45300 | B2: Nextleap DAF | C2: 0 | D2: ₹120,000.00 | E2: =IF(D2="",0,D2) -> ₹120,000.00 | F2: Nextleap DAF | G2: Salary | H2: Income
A3: 45300 | B3: Drink | C3: ₹120.00 | E3: =IF(D3="",0,D3) -> 0 | F3: Coffee | G3: Dining Out | H3: Expense
A4: 45301 | B4: Flat Expenses | C4: ₹21,600.00 | E4: =IF(D4="",0,D4) -> 0 | F4: Rent | G4: Living Expenses | H4: Expense
A5: 45301 | B5: EMI | C5: ₹3,600.00 | E5: =IF(D5="",0,D5) -> 0 | F5: Cash loan | G5: Transport | H5: Expense
A6: 45301 | B6: Drink | C6: ₹120.00 | E6: =IF(D6="",0,D6) -> 0 | F6: Coffee | G6: Dining Out | H6: Expense
A7: 45302 | B7: Drink | C7: ₹120.00 | E7: =IF(D7="",0,D7) -> 0 | F7: Coffee | G7: Dining Out | H7: Expense
A8: 45303 | B8: Drink | C8: ₹120.00 | E8: =IF(D8="",0,D8) -> 0 | F8: Coffee | G8: Dining Out | H8: Expense
A9: 45304 | B9: Drink | C9: ₹120.00 | E9: =IF(D9="",0,D9) -> 0 | F9: Coffee | G9: Dining Out | H9: Expense
A10: 45304 | B10: Green's | C10: ₹3,720.00 | E10: =IF(D10="",0,D10) -> 0 | F10: Groceries | G10: Living Expenses | H10: Expense
A11: 45307 | B11: Power source | C11: ₹1,200.00 | E11: =IF(D11="",0,D11) -> 0 | F11: Gas/Electrics | G11: Living Expenses | H11: Expense
A12: 45307 | B12: Drink | C12: ₹120.00 | E12: =IF(D12="",0,D12) -> 0 | F12: Coffee | G12: Dining Out | H12: Expense
A13: 45308 | B13: Drink | C13: ₹120.00 | E13: =IF(D13="",0,D13) -> 0 | F13: Coffee | G13: Dining Out | H13: Expense
A14: 45309 | B14: Fuel | C14: ₹1,848.00 | E14: =IF(D14="",0,D14) -> 0 | F14: Coffee | G14: Dining Out | H14: Expense
... A23: 45313 | B23: Ola | C23: ₹672.00 | E23: =IF(D23="",0,D23) -> 0 | F23: Taxi | G23: Transport | H23: Expense
A24: 45314 | B24: Onlne earning | C24: 0 | D24: ₹108,000.00 | E24: =IF(D24="",0,D24) -> ₹108,000.00 | F24: YouTube | G24: Passive | H24: Income
A25: 45314 | B25: Drink | C25: ₹120.00 | E25: =IF(D25="",0,D25) -> 0 | F25: Coffee | G25: Dining Out | H25: Expense
A26: 45315 | B26: Drink | C26: ₹120.00 | E26: =IF(D26="",0,D26) -> 0 | F26: Coffee | G26: Dining Out | H26: Expense
A27: 45315 | B27: Onlne earning | C27: 0 | D27: ₹108,000.00 | E27: =IF(D27="",0,D27) -> ₹108,000.00 | F27: Teachable | G27: Passive | H27: Income
A28: 45315 | B28: Phone | C28: ₹960.00 | E28: =IF(D28="",0,D28) -> 0 | F28: Phone | G28: Living Expenses | H28: Expense
A29: 45316 | B29: Family and Friends surprises | C29: ₹1,080.00 | E29: =IF(D29="",0,D29) -> 0 | F29: Gifts | G29: Discretionary | H29: Expense
A30: 45316 | B30: Online streaming | C30: ₹768.00 | E30: =IF(D30="",0,D30) -> 0 | F30: Entertainment | G30: Discretionary | H30: Expense
A31: 45316 | B31: Drink | C31: ₹120.00 | E31: =IF(D31="",0,D31) -> 0 | F31: Coffee | G31: Dining Out | H31: Expense
A32: 45317 | B32: Drink | C32: ₹120.00 | E32: =IF(D32="",0,D32) -> 0 | F32: Coffee | G32: Dining Out | H32: Expense
A33: 45318 | B33: Drink | C33: ₹120.00 | E33: =IF(D33="",0,D33) -> 0 | F33: Coffee | G33: Dining Out | H33: Expense
A34: 45318 | B34: Green's | C34: ₹4,080.00 | E34: =IF(D34="",0,D34) -> 0 | F34: Groceries | G34: Living Expenses | H34: Expense
A35: 45319 | B35: Office Lunch | C35: ₹888.00 | E35: =IF(D35="",0,D35) -> 0 | F35: Restaurant | G35: Dining Out | H35: Expense
A36: 45320 | B36: Evening snacks | C36: ₹288.00 | E36: =IF(D36="",0,D36) -> 0 | F36: Restaurant | G36: Dining Out | H36: Expense
A37: 45321 | B37: Orphanage | C37: ₹1,320.00 | E37: =IF(D37="",0,D37) -> 0 | F37: Donation | G37: Charity | H37: Expense
A38: 45321 | B38: Fuel | C38: ₹1,512.00 | E38: =IF(D38="",0,D38) -> 0 | F38: Fueling | G38: Transport | H38: Expense
A39: 45321 | B39: Drink | C39: ₹120.00 | E39: =IF(D39="",0,D39) -> 0 | F39: Coffee | G39: Dining Out | H39: Expense
... A48: 45327 | B48: Ola | C48: ₹552.00 | E48: =IF(D48="",0,D48) -> 0 | F48: Taxi | G48: Transport | H48: Expense
A49: 45328 | B49: Nextleap DAF | C49: 0 | D49: ₹120,000.00 | E49: =IF(D49="",0,D49) -> ₹120,000.00 | F49: Data with Decision | G49: Salary | H49: Income
A50: 45328 | B50: Drink | C50: ₹120.00 | E50: =IF(D50="",0,D50) -> 0 | F50: Coffee | G50: Dining Out | H50: Expense
A51: 45329 | B51: Flat Expenses | C51: ₹21,600.00 | E51: =IF(D51="",0,D51) -> 0 | F51: Rent | G51: Living Expenses | H51: Expense
A52: 45329 | B52: EMI | C52: ₹3,600.00 | E52: =IF(D52="",0,D52) -> 0 | F52: Cash loan | G52: Transport | H52: Expense
A53: 45329 | B53: Drink | C53: ₹120.00 | E53: =IF(D53="",0,D53) -> 0 | F53: Coffee | G53: Dining Out | H53: Expense
A54: 45330 | B54: Drink | C54: ₹120.00 | E54: =IF(D54="",0,D54) -> 0 | F54: Coffee | G54: Dining Out | H54: Expense
A55: 45331 | B55: Drink | C55: ₹120.00 | E55: =IF(D55="",0,D55) -> 0 | F55: Coffee | G55: Dining Out | H55: Expense
A56: 45332 | B56: Drink | C56: ₹120.00 | E56: =IF(D56="",0,D56) -> 0 | F56: Coffee | G56: Dining Out | H56: Expense
A57: 45332 | B57: Green's | C57: ₹4,920.00 | E57: =IF(D57="",0,D57) -> 0 | F57: Groceries | G57: Living Expenses | H57: Expense
A58: 45335 | B58: Power source | C58: ₹1,226.40 | E58: =IF(D58="",0,D58) -> 0 | F58: Gas/Electrics | G58: Living Expenses | H58: Expense
A59: 45335 | B59: Drink | C59: ₹120.00 | E59: =IF(D59="",0,D59) -> 0 | F59: Coffee | G59: Dining Out | H59: Expense
A60: 45336 | B60: Drink | C60: ₹120.00 | E60: =IF(D60="",0,D60) -> 0 | F60: Coffee | G60: Dining Out | H60: Expense
A61: 45337 | B61: Fuel | C61: ₹1,872.00 | E61: =IF(D61="",0,D61) -> 0 | F61: Fueling | G61: Transport | H61: Expense
... A70: 45341 | B70: Ola | C70: ₹693.60 | E70: =IF(D70="",0,D70) -> 0 | F70: Taxi | G70: Transport | H70: Expense
A71: 45342 | B71: Onlne earning | C71: 0 | D71: ₹19,200.00 | E71: =IF(D71="",0,D71) -> ₹19,200.00 | F71: YouTube | G71: Passive | H71: Income
A72: 45342 | B72: Drink | C72: ₹120.00 | E72: =IF(D72="",0,D72) -> 0 | F72: Coffee | G72: Dining Out | H72: Expense
A73: 45343 | B73: Drink | C73: ₹120.00 | E73: =IF(D73="",0,D73) -> 0 | F73: Coffee | G73: Dining Out | H73: Expense
A74: 45343 | B74: Phone | C74: ₹960.00 | E74: =IF(D74="",0,D74) -> 0 | F74: Phone | G74: Living Expenses | H74: Expense
A75: 45344 | B75: Family and Friends surprises | C75: ₹1,101.60 | E75: =IF(D75="",0,D75) -> 0 | F75: Gifts | G75: Discretionary | H75: Expense
A76: 45344 | B76: Online streaming | C76: ₹840.00 | E76: =IF(D76="",0,D76) -> 0 | F76: Entertainment | G76: Discretionary | H76: Expense
A77: 45344 | B77: Drink | C77: ₹120.00 | E77: =IF(D77="",0,D77) -> 0 | F77: Coffee | G77: Dining Out | H77: Expense
A78: 45345 | B78: Drink | C78: ₹120.00 | E78: =IF(D78="",0,D78) -> 0 | F78: Coffee | G78: Dining Out | H78: Expense
A79: 45346 | B79: Drink | C79: ₹120.00 | E79: =IF(D79="",0,D79) -> 0 | F79: Coffee | G79: Dining Out | H79: Expense
A80: 45346 | B80: Green's | C80: ₹4,104.00 | E80: =IF(D80="",0,D80) -> 0 | F80: Groceries | G80: Living Expenses | H80: Expense
A81: 45347 | B81: Office Lunch | C81: ₹909.60 | E81: =IF(D81="",0,D81) -> 0 | F81: Restaurant | G81: Dining Out | H81: Expense
A82: 45348 | B82: Evening snacks | C82: ₹309.60 | E82: =IF(D82="",0,D82) -> 0 | F82: Restaurant | G82: Dining Out | H82: Expense
A83: 45349 | B83: Orphanage | C83: ₹1,320.00 | E83: =IF(D83="",0,D83) -> 0 | F83: Donation | G83: Charity | H83: Expense
... A94: 45355 | B94: Ola | C94: ₹578.40 | E94: =IF(D94="",0,D94) -> 0 | F94: Taxi | G94: Transport | H94: Expense
A95: 45356 | B95: Nextleap DAF | C95: 0 | D95: ₹120,000.00 | E95: =IF(D95="",0,D95) -> ₹120,000.00 | F95: Data with Decision | G95: Salary | H95: Income
A96: 45356 | B96: Drink | C96: ₹120.00 | E96: =IF(D96="",0,D96) -> 0 | F96: Coffee | G96: Dining Out | H96: Expense
A97: 45357 | B97: Flat Expenses | C97: ₹21,600.00 | E97: =IF(D97="",0,D97) -> 0 | F97: Rent | G97: Living Expenses | H97: Expense
A98: 45357 | B98: EMI | C98: ₹3,600.00 | E98: =IF(D98="",0,D98) -> 0 | F98: Cash loan | G98: Transport | H98: Expense
A99: 45357 | B99: Drink | C99: ₹120.00 | E99: =IF(D99="",0,D99) -> 0 | F99: Coffee | G99: Dining Out | H99: Expense
A100: 45358 | B100: Drink | C100: ₹120.00 | E100: =IF(D100="",0,D100) -> 0 | F100: Coffee | G100: Dining Out | H100: Expense
A101: 45359 | B101: Drink | C101: ₹120.00 | E101: =IF(D101="",0,D101) -> 0 | F101: Coffee | G101: Dining Out | H101: Expense
A102: 45360 | B102: Drink | C102: ₹120.00 | E102: =IF(D102="",0,D102) -> 0 | F102: Coffee | G102: Dining Out | H102: Expense
A103: 45360 | B103: Green's | C103: ₹3,576.00 | E103: =IF(D103="",0,D103) -> 0 | F103: Groceries | G103: Living Expenses | H103: Expense
A104: 45363 | B104: Power source | C104: ₹1,250.40 | E104: =IF(D104="",0,D104) -> 0 | F104: Gas/Electrics | G104: Living Expenses | H104: Expense
A105: 45363 | B105: Drink | C105: ₹120.00 | E105: =IF(D105="",0,D105) -> 0 | F105: Coffee | G105: Dining Out | H105: Expense
A106: 45364 | B106: Drink | C106: ₹120.00 | E106: =IF(D106="",0,D106) -> 0 | F106: Coffee | G106: Dining Out | H106: Expense
A107: 45365 | B107: Fuel | C107: ₹1,893.60 | E107: =IF(D107="",0,D107) -> 0 | F107: Fueling | G107: Transport | H107: Expense
... A116: 45369 | B116: Ola | C116: ₹720.00 | E116: =IF(D116="",0,D116) -> 0 | F116: Taxi | G116: Transport | H116: Expense
A117: 45370 | B117: Onlne earning | C117: 0 | D117: ₹24,000.00 | E117: =IF(D117="",0,D117) -> ₹24,000.00 | F117: YouTube | G117: Passive | H117: Income
A118: 45370 | B118: Drink | C118: ₹120.00 | E118: =IF(D118="",0,D118) -> 0 | F118: Coffee | G118: Dining Out | H118: Expense
A119: 45371 | B119: Drink | C119: ₹120.00 | E119: =IF(D119="",0,D119) -> 0 | F119: Coffee | G119: Dining Out | H119: Expense
A120: 45371 | B120: Taken medication | C120: ₹1,800.00 | E120: =IF(D120="",0,D120) -> 0 | F120: Doctor | G120: Medical | H120: Expense
A121: 45371 | B121: Phone | C121: ₹960.00 | E121: =IF(D121="",0,D121) -> 0 | F121: Phone | G121: Living Expenses | H121: Expense
A122: 45372 | B122: Family and Friends surprises | C122: ₹1,123.20 | E122: =IF(D122="",0,D122) -> 0 | F122: Gifts | G122: Discretionary | H122: Expense
A123: 45372 | B123: Online streaming | C123: ₹840.00 | E123: =IF(D123="",0,D123) -> 0 | F123: Entertainment | G123: Discretionary | H123: Expense
A124: 45372 | B124: Drink | C124: ₹120.00 | E124: =IF(D124="",0,D124) -> 0 | F124: Coffee | G124: Dining Out | H124: Expense
A125: 45373 | B125: Drink | C125: ₹120.00 | E125: =IF(D125="",0,D125) -> 0 | F125: Coffee | G125: Dining Out | H125: Expense
A126: 45374 | B126: Drink | C126: ₹120.00 | E126: =IF(D126="",0,D126) -> 0 | F126: Coffee | G126: Dining Out | H126: Expense
A127: 45374 | B127: Green's | C127: ₹4,125.60 | E127: =IF(D127="",0,D127) -> 0 | F127: Groceries | G127: Living Expenses | H127: Expense
A128: 45375 | B128: Office Lunch | C128: ₹936.00 | E128: =IF(D128="",0,D128) -> 0 | F128: Restaurant | G128: Dining Out | H128: Expense
A129: 45376 | B129: Evening snacks | C129: ₹336.00 | E129: =IF(D129="",0,D129) -> 0 | F129: Restaurant | G129: Dining Out | H129: Expense
... A144: 45386 | B144: Drink | C144: ₹120.00 | E144: =IF(D144="",0,D144) -> 0 | F144: Coffee | G144: Dining Out | H144: Expense
A145: 45387 | B145: Nextleap DAF | C145: 0 | D145: ₹120,000.00 | E145: =IF(D145="",0,D145) -> ₹120,000.00 | F145: Data with Decision | G145: Salary | H145: Income
A146: 45387 | B146: Drink | C146: ₹120.00 | E146: =IF(D146="",0,D146) -> 0 | F146: Coffee | G146: Dining Out | H146: Expense
A147: 45388 | B147: Flat Expenses | C147: ₹21,600.00 | E147: =IF(D147="",0,D147) -> 0 | F147: Rent | G147: Living Expenses | H147: Expense
A148: 45388 | B148: EMI | C148: ₹3,600.00 | E148: =IF(D148="",0,D148) -> 0 | F148: Cash loan | G148: Transport | H148: Expense
A149: 45388 | B149: Drink | C149: ₹120.00 | E149: =IF(D149="",0,D149) -> 0 | F149: Coffee | G149: Dining Out | H149: Expense
A150: 45389 | B150: Drink | C150: ₹120.00 | E150: =IF(D150="",0,D150) -> 0 | F150: Coffee | G150: Dining Out | H150: Expense
A151: 45390 | B151: Drink | C151: ₹120.00 | E151: =IF(D151="",0,D151) -> 0 | F151: Coffee | G151: Dining Out | H151: Expense
A152: 45391 | B152: Drink | C152: ₹120.00 | E152: =IF(D152="",0,D152) -> 0 | F152: Coffee | G152: Dining Out | H152: Expense
A153: 45391 | B153: Green's | C153: ₹3,796.80 | E153: =IF(D153="",0,D153) -> 0 | F153: Groceries | G153: Living Expenses | H153: Expense
A154: 45394 | B154: Power source | C154: ₹1,276.80 | E154: =IF(D154="",0,D154) -> 0 | F154: Gas/Electrics | G154: Living Expenses | H154: Expense
A155: 45394 | B155: Drink | C155: ₹120.00 | E155: =IF(D155="",0,D155) -> 0 | F155: Coffee | G155: Dining Out | H155: Expense
A156: 45395 | B156: Drink | C156: ₹120.00 | E156: =IF(D156="",0,D156) -> 0 | F156: Coffee | G156: Dining Out | H156: Expense
...

Sheet clean_data
A1: Date | B1: Description | C1: Debit | D1: Credit | E1: Sub-category | F1: Category | G1: Category Type | H1: month | I1: weekday | Y1: Debit
A2: 45300 | B2: Nextleap DAF | C2: 0 | D2: 120000 | E2: Nextleap DAF | F2: Salary | G2: Income | H2: =TEXT(A2,"MMM-YYYY") -> Jan-2024 | I2: =WEEKNUM(A2,2) -> 2 | Y2: 0
A3: 45300 | B3: Drink | C3: 120 | D3: 0 | E3: Coffee | F3: Dining Out | G3: Expense | H3: =TEXT(A3,"MMM-YYYY") -> Jan-2024 | I3: =WEEKNUM(A3,2) -> 2 | K3: =SUM(C2:C487) -> 724584 | Y3: 120
A4: 45301 | B4: Flat Expenses | C4: 21600 | D4: 0 | E4: Rent | F4: Living Expenses | G4: Expense | H4: =TEXT(A4,"MMM-YYYY") -> Jan-2024 | I4: =WEEKNUM(A4,2) -> 2 | Y4: 21600
A5: 45301 | B5: EMI | C5: 3600 | D5: 0 | E5: Cash loan | F5: Transport | G5: Expense | H5: =TEXT(A5,"MMM-YYYY") -> Jan-2024 | I5: =WEEKNUM(A5,2) -> 2 | K5: 724584 | Y5: 3600
A6: 45301 | B6: Drink | C6: 120 | D6: 0 | E6: Coffee | F6: Dining Out | G6: Expense | H6: =TEXT(A6,"MMM-YYYY") -> Jan-2024 | I6: =WEEKNUM(A6,2) -> 2 | Y6: 120
A7: 45302 | B7: Drink | C7: 120 | D7: 0 | E7: Coffee | F7: Dining Out | G7: Expense | H7: =TEXT(A7,"MMM-YYYY") -> Jan-2024 | I7: =WEEKNUM(A7,2) -> 2 | Y7: 120
A8: 45303 | B8: Drink | C8: 120 | D8: 0 | E8: Coffee | F8: Dining Out | G8: Expense | H8: =TEXT(A8,"MMM-YYYY") -> Jan-2024 | I8: =WEEKNUM(A8,2) -> 2 | Y8: 120
A9: 45304 | B9: Drink | C9: 120 | D9: 0 | E9: Coffee | F9: Dining Out | G9: Expense | H9: =TEXT(A9,"MMM-YYYY") -> Jan-2024 | I9: =WEEKNUM(A9,2) -> 2 | Y9: 120
A10: 45304 | B10: Green's | C10: 3720 | D10: 0 | E10: Groceries | F10: Living Expenses | G10: Expense | H10: =TEXT(A10,"MMM-YYYY") -> Jan-2024 | I10: =WEEKNUM(A10,2) -> 2 | K10: =SUM(D2:D487) -> 1570560 | Y10: 3720
A11: 45307 | B11: Power source | C11: 1200 | D11: 0 | E11: Gas/Electrics | F11: Living Expenses | G11: Expense | H11: =TEXT(A11,"MMM-YYYY") -> Jan-2024 | I11: =WEEKNUM(A11,2) -> 3 | Y11: 1200
A12: 45307 | B12: Drink | C12: 120 | D12: 0 | E12: Coffee | F12: Dining Out | G12: Expense | H12: =TEXT(A12,"MMM-YYYY") -> Jan-2024 | I12: =WEEKNUM(A12,2) -> 3 | Y12: 120
A13: 45308 | B13: Drink | C13: 120 | D13: 0 | E13: Coffee | F13: Dining Out | G13: Expense | H13: =TEXT(A13,"MMM-YYYY") -> Jan-2024 | I13: =WEEKNUM(A13,2) -> 3 | Y13: 120
A14: 45309 | B14: Fuel | C14: 1848 | D14: 0 | E14: Coffee | F14: Dining Out | G14: Expense | H14: =TEXT(A14,"MMM-YYYY") -> Jan-2024 | I14: =WEEKNUM(A14,2) -> 3 | Y14: 1848
A15: 45309 | B15: Drink | C15: 120 | D15: 0 | E15: Coffee | F15: Dining Out | G15: Expense | H15: =TEXT(A15,"MMM-YYYY") -> Jan-2024 | I15: =WEEKNUM(A15,2) -> 3 | Y15: 120
A16: 45310 | B16: Drink | C16: 120 | D16: 0 | E16: Coffee | F16: Dining Out | G16: Expense | H16: =TEXT(A16,"MMM-YYYY") -> Jan-2024 | I16: =WEEKNUM(A16,2) -> 3 | Y16: 120
A17: 45311 | B17: Green's | C17: 3240 | D17: 0 | E17: Groceries | F17: Living Expenses | G17: Expense | H17: =TEXT(A17,"MMM-YYYY") -> Jan-2024 | I17: =WEEKNUM(A17,2) -> 3 | Y17: 3240
A18: 45311 | B18: Drink | C18: 120 | D18: 0 | E18: Coffee | F18: Dining Out | G18: Expense | H18: =TEXT(A18,"MMM-YYYY") -> Jan-2024 | I18: =WEEKNUM(A18,2) -> 3 | Y18: 120
A19: 45312 | B19: Drink | C19: 120 | D19: 0 | E19: Coffee | F19: Dining Out | G19: Expense | H19: =TEXT(A19,"MMM-YYYY") -> Jan-2024 | I19: =WEEKNUM(A19,2) -> 3 | Y19: 120
A20: 45312 | B20: Cinemas | C20: 960 | D20: 0 | E20: Entertainment | F20: Discretionary | G20: Expense | H20: =TEXT(A20,"MMM-YYYY") -> Jan-2024 | I20: =WEEKNUM(A20,2) -> 3 | Y20: 960
A21: 45312 | B21: Zara Clothes | C21: 2352 | D21: 0 | E21: Clothes | F21: Discretionary | G21: Expense | H21: =TEXT(A21,"MMM-YYYY") -> Jan-2024 | I21: =WEEKNUM(A21,2) -> 3 | Y21: 2352
A22: 45312 | B22: Swiggy | C22: 1248 | D22: 0 | E22: Restaurant | F22: Dining Out | G22: Expense | H22: =TEXT(A22,"MMM-YYYY") -> Jan-2024 | I22: =WEEKNUM(A22,2) -> 3 | Y22: 1248
... A487: 45600 | B487: Foodary | C487: 360 | D487: 0 | E487: Restaurant | F487: Dining Out | G487: Expense | H487: =TEXT(A487,"MMM-YYYY") -> Nov-2024 | I487: =WEEKNUM(A487,2) -> 45 | Y487: 360

Sheet discraptive staticts
A3: Debit
A4: mean | B4: =ROUND(AVERAGE(clean_data!C2:C487),2) -> 1490.91
A5: median | B5: =MEDIAN(clean_data!C2:C487) -> 120
A6: mode | B6: =MODE(clean_data!C2:C487) -> 120
A11: Credit
A12: mean | B12: =ROUND(AVERAGE(clean_data!D2:D487),2) -> 3231.6
A13: median | B13: =MEDIAN(clean_data!D2:D487) -> 0
A14: mode | B14: =MODE(clean_data!D2:D487) -> 0

Sheet pivot table
A2: Category and sum_debit | E2: Category Type | F2: Sum of Debit | G2: Sum of Credit
A3: Category | B3: Sum of Debit | E3: Expense | F3: 724584 | G3: 0
A4: Charity | B4: 13200 | E4: Income | F4: 0 | G4: 1570560
A5: Dining Out | B5: 59373.6 | E5: Grand Total | F5: 724584 | G5: 1570560
A6: Discretionary | B6: 168662.4
A7: Living Expenses | B7: 393595.2
A8: Medical | B8: 5400
A9: Transport | B9: 84352.8
A10: Grand Total | B10: 724584 | E10: category and sum of credit
E11: Category | F11: Sum of Credit
E12: Passive | F12: 370560
A13: month | B13: Sum of Debit | C13: Sum of Credit | E13: Salary | F13: 1200000
A14: Apr-2024 | B14: 62592 | C14: 176160 | E14: Grand Total | F14: 1570560
A15: Aug-2024 | B15: 72573.6 | C15: 139200
A16: Feb-2024 | B16: 70646.4 | C16: 139200 | I16: Category Type | J16: Income
A17: Jan-2024 | B17: 53496 | C17: 336000
A18: Jul-2024 | B18: 72832.8 | C18: 124800 | I18: Category | J18: Sub-category | K18: Sum of Credit
A19: Jun-2024 | B19: 69372 | C19: 122400 | I19: Passive | J19: Teachable | K19: 108000
A20: Mar-2024 | B20: 83006.4 | C20: 144000 | J20: YouTube | K20: 262560
A21: May-2024 | B21: 76272 | C21: 144000 | I21: Passive Total | K21: 370560
A22: Nov-2024 | B22: 17251.2 | C22: 0 | I22: Salary | J22: Data with Decision | K22: 1080000
A23: Oct-2024 | B23: 74889.6 | C23: 122400 | J23: Nextleap DAF | K23: 120000
A24: Sep-2024 | B24: 71652 | C24: 122400 | I24: Salary Total | K24: 1200000
A25: Grand Total | B25: 724584 | C25: 1570560 | I25: Grand Total | K25: 1570560
A46: weekday | B46: Sum of Debit | C46: Sum of Credit
A47: 2 | B47: 29520 | C47: 120000
A48: 3 | B48: 11568 | C48: 0
A49: 4 | B49: 9048 | C49: 216000
A50: 5 | B50: 14808 | C50: 0
A51: 6 | B51: 34752 | C51: 120000
A52: 7 | B52: 11709.6 | C52: 0
A53: 8 | B53: 9208.8 | C53: 19200
A54: 9 | B54: 13987.2 | C54: 0
A55: 10 | B55: 33460.8 | C55: 120000
A56: 11 | B56: 11848.8 | C56: 0
A57: 12 | B57: 11104.8 | C57: 24000
A58: 13 | B58: 16132.8 | C58: 0
... A90: 45 | B90: 4838.4 | C90: 0
A91: Grand Total | B91: 724584 | C91: 1570560
A97: Category Type | B97: Income
A99: Category | B99: Sub-category | C99: Sum of Credit
A100: Passive | B100: Teachable | C100: 108000
B101: YouTube | C101: 262560
A102: Passive Total | C102: 370560
A103: Salary | B103: Data with Decision | C103: 1080000
B104: Nextleap DAF | C104: 120000
A105: Salary Total | C105: 1200000
A106: Grand Total | C106: 1570560

Sheet Dashborad
E16: Category | F16: Sum of Debit
E17: Charity | F17: 13200
E18: Dining Out | F18: 59373.6
E19: Discretionary | F19: 168662.4 | N19: Category Type | O19: Sum of Debit | P19: Sum of Credit
E20: Living Expenses | F20: 393595.2 | N20: Expense | O20: 724584 | P20: 0
E21: Medical | F21: 5400 | N21: Income | O21: 0 | P21: 1570560
E22: Passive | F22: 0 | N22: Grand Total | O22: 724584 | P22: 1570560
E23: Salary | F23: 0
E24: Transport | F24: 84352.8
E25: Grand Total | F25: 724584
E32: month | F32: Sum of Debit | G32: Sum of Credit
E33: Apr-2024 | F33: 62592 | G33: 176160
E34: Aug-2024 | F34: 72573.6 | G34: 139200
E35: Feb-2024 | F35: 70646.4 | G35: 139200
E36: Jan-2024 | F36: 53496 | G36: 336000
E37: Jul-2024 | F37: 72832.8 | G37: 124800
E38: Jun-2024 | F38: 69372 | G38: 122400
E39: Mar-2024 | F39: 83006.4 | G39: 144000
E40: May-2024 | F40: 76272 | G40: 144000
E41: Nov-2024 | F41: 17251.2 | G41: 0
E42: Oct-2024 | F42: 74889.6 | G42: 122400
E43: Sep-2024 | F43: 71652 | G43: 122400
E44: Grand Total | F44: 724584 | G44: 1570560
L99: Category | M99: Sub-category | N99: Sum of Credit
L100: Passive | M100: Teachable | N100: 108000
M101: YouTube | N101: 262560
L102: Passive Total | N102: 370560
L103: Salary | M103: Data with Decision | N103: 1080000
M104: Nextleap DAF | N104: 120000
L105: Salary Total | N105: 1200000
L106: Grand Total | N106: 1570560

Sheet insights
C2: Insights & Recommendations
B3: 1 | C3: Major expense category – Living costs take up the largest share of spending.
B4: 2 | C4: Highest expense surge – Noticed in March and particularly during the 15th week.
B5: 3 | C5: Monthly financial balance – Typically shows a surplus (savings).
B6: 4 | C6: Income reliance – Depends mainly on two primary income sources.
B7: 5 | C7: Practical recommendations –
C8: Maintain the current 54% savings rate and allocate more funds toward investments.
C9: Look for opportunities to lower living costs wherever possible.
C10: Explore new income channels to improve financial resilience.
C11: Set aside an emergency fund of around ₹3.6L, which equals about six months of expenses.
C14: Conclusion
C15: Overall, the financial position appears healthy with a consistent savings surplus and a disciplined savings rate of 54%. However, dependency on two primary income sources and relatively high living expenses indicate areas for improvement. By continuing to invest savings, reducing discretionary spending, and creating an emergency reserve, long-term financial security and resilience can be further strengthened.
